wfgenes/__init__.py
wfgenes/wfgenes_gui.py
wfgenes/core/BUILTIN.py
wfgenes/core/__init__.py
wfgenes/core/builtin_wfgenes.py
wfgenes/core/clean_wfgenes.py
wfgenes/core/dask_executor.cfg
wfgenes/core/dask_import.cfg
wfgenes/core/dask_wfgenes.py
wfgenes/core/dot_wfgenes.py
wfgenes/core/executor_arg_parser.cfg
wfgenes/core/fireworks_wfgenes.py
wfgenes/core/initial_wfgenes.py
wfgenes/core/parsl_config.cfg
wfgenes/core/parsl_import.cfg
wfgenes/core/parsl_wfgenes.py
wfgenes/core/pywrapper_wfgenes.py
wfgenes/core/resources.yml
wfgenes/core/rgg_to_wconfig.py
wfgenes/core/run_pywrapper.py
wfgenes/core/simstack_wfgenes.py
wfgenes/core/wconfig_schema.json
wfgenes/core/wfgenes.yml
wfgenes/core/wfgenes_executor.py
wfgenes/core/wfgenes_generator.py
wfgenes/core/wgenerator.py
wfgenes/engine/__init__.py
wfgenes/engine/wfengine.py
wfgenes/engine/wfengine_jupyter.py
wfgenes/engine/wfengine_remote.py
wfgenes/engine/wfengine_test.py
wfgenes/fig/notebook.png
wfgenes/fig/slurm_multi.png
wfgenes/fig/slurm_single.png
wfgenes/fig/wfgenes_logo.png
wfgenes/intro_examples/__init__.py
wfgenes/intro_examples/coupling_workflow/__init__.py
wfgenes/intro_examples/coupling_workflow/coupled_workflow.yml
wfgenes/intro_examples/coupling_workflow/wconfig_simple.yaml
wfgenes/intro_examples/coupling_workflow/.ipynb_checkpoints/coupled_workflow-checkpoint.yml
wfgenes/intro_examples/coupling_workflow/.ipynb_checkpoints/wconfig_simple-checkpoint.yaml
wfgenes/intro_examples/coupling_workflow/inputs/__init__.py
wfgenes/intro_examples/coupling_workflow/inputs/constant_y.yaml
wfgenes/intro_examples/coupling_workflow/inputs/constant_z.yaml
wfgenes/intro_examples/coupling_workflow/inputs/data.yaml
wfgenes/intro_examples/coupling_workflow/inputs/list_length.yaml
wfgenes/intro_examples/ct-workflow/__init__.py
wfgenes/intro_examples/ct-workflow/morphology.yaml
wfgenes/intro_examples/ct-workflow/parameters.yaml
wfgenes/intro_examples/ct-workflow/reorganization_energy.yaml
wfgenes-1.0.9.dist-info/LICENSE
wfgenes-1.0.9.dist-info/METADATA
wfgenes-1.0.9.dist-info/WHEEL
wfgenes-1.0.9.dist-info/entry_points.txt
wfgenes-1.0.9.dist-info/top_level.txt
wfgenes-1.0.9.dist-info/RECORD
